muchstuff/__init__.py
muchstuff/_debug.py
muchstuff/main.py
muchstuff/manager.py
muchstuff/tui.py
muchstuff/tui.tcss
muchstuff/vcs.py
muchstuff-0.4.4.dist-info/METADATA
muchstuff-0.4.4.dist-info/WHEEL
muchstuff-0.4.4.dist-info/entry_points.txt
muchstuff-0.4.4.dist-info/licenses/LICENSE
muchstuff-0.4.4.dist-info/RECORD
