Metadata-Version: 2.4
Name: muchstuff
Version: 0.4.4
Summary: A TUI helper to keep code repositories up to date
Project-URL: homepage, https://github.com/yggdr/muchstuff
Project-URL: github, https://github.com/yggdr/muchstuff
Author-email: Konstantin Schukraft <muchstuff@schukraft.org>
License: ISC License
License-File: LICENSE
Classifier: Development Status :: 4 - Beta
Classifier: Environment :: Console
Classifier: Intended Audience :: Developers
Classifier: License :: OSI Approved :: ISC License (ISCL)
Classifier: Natural Language :: English
Classifier: Operating System :: POSIX
Classifier: Operating System :: Unix
Classifier: Programming Language :: Python
Classifier: Programming Language :: Python :: 3
Classifier: Programming Language :: Python :: 3 :: Only
Classifier: Programming Language :: Python :: 3.10
Classifier: Programming Language :: Python :: 3.11
Classifier: Programming Language :: Python :: 3.12
Classifier: Programming Language :: Python :: 3.13
Classifier: Topic :: Software Development
Classifier: Topic :: Software Development :: Version Control :: Git
Classifier: Topic :: Utilities
Requires-Python: >=3.10
Requires-Dist: textual<3,>=1.0.0
Requires-Dist: tomli~=2.2.0; python_full_version < '3.11'
Requires-Dist: typing-extensions~=4.12.2; python_full_version < '3.11'
Requires-Dist: unidiff
Provides-Extra: debug
Requires-Dist: aiomonitor; extra == 'debug'
Requires-Dist: remote-pdb; extra == 'debug'
